[{"code":"FC","title":"Freight Class Types","level":1,"parent_code":null,"sector_code":null,"is_leaf":false,"children_count":18},{"code":"FC.01","title":"Class 50 (Heaviest/Densest)","level":2,"parent_code":"FC","sector_code":null,"is_leaf":false,"children_count":0},{"code":"FC.02","title":"Class 55","level":2,"parent_code":"FC","sector_code":null,"is_leaf":false,"children_count":0},{"code":"FC.03","title":"Class 60","level":2,"parent_code":"FC","sector_code":null,"is_leaf":false,"children_count":0},{"code":"FC.04","title":"Class 65","level":2,"parent_code":"FC","sector_code":null,"is_leaf":false,"children_count":0},{"code":"FC.05","title":"Class 70","level":2,"parent_code":"FC","sector_code":null,"is_leaf":false,"children_count":0},{"code":"FC.06","title":"Class 77.5","level":2,"parent_code":"FC","sector_code":null,"is_leaf":false,"children_count":0},{"code":"FC.07","title":"Class 85","level":2,"parent_code":"FC","sector_code":null,"is_leaf":false,"children_count":0},{"code":"FC.08","title":"Class 92.5","level":2,"parent_code":"FC","sector_code":null,"is_leaf":false,"children_count":0},{"code":"FC.09","title":"Class 100","level":2,"parent_code":"FC","sector_code":null,"is_leaf":false,"children_count":0},{"code":"FC.10","title":"Class 110","level":2,"parent_code":"FC","sector_code":null,"is_leaf":false,"children_count":0},{"code":"FC.11","title":"Class 125","level":2,"parent_code":"FC","sector_code":null,"is_leaf":false,"children_count":0},{"code":"FC.12","title":"Class 150","level":2,"parent_code":"FC","sector_code":null,"is_leaf":false,"children_count":0},{"code":"FC.13","title":"Class 175","level":2,"parent_code":"FC","sector_code":null,"is_leaf":false,"children_count":0},{"code":"FC.14","title":"Class 200","level":2,"parent_code":"FC","sector_code":null,"is_leaf":false,"children_count":0},{"code":"FC.15","title":"Class 250","level":2,"parent_code":"FC","sector_code":null,"is_leaf":false,"children_count":0},{"code":"FC.16","title":"Class 300","level":2,"parent_code":"FC","sector_code":null,"is_leaf":false,"children_count":0},{"code":"FC.17","title":"Class 400","level":2,"parent_code":"FC","sector_code":null,"is_leaf":false,"children_count":0},{"code":"FC.18","title":"Class 500 (Lightest/Least Dense)","level":2,"parent_code":"FC","sector_code":null,"is_leaf":false,"children_count":0}]