[{"code":"LU","title":"Labor Union Types","level":1,"parent_code":null,"sector_code":null,"is_leaf":false,"children_count":12},{"code":"LU.01","title":"Craft Union","level":2,"parent_code":"LU","sector_code":null,"is_leaf":false,"children_count":0},{"code":"LU.02","title":"Industrial Union","level":2,"parent_code":"LU","sector_code":null,"is_leaf":false,"children_count":0},{"code":"LU.03","title":"General Union","level":2,"parent_code":"LU","sector_code":null,"is_leaf":false,"children_count":0},{"code":"LU.04","title":"White-Collar Union","level":2,"parent_code":"LU","sector_code":null,"is_leaf":false,"children_count":0},{"code":"LU.05","title":"Public Sector Union","level":2,"parent_code":"LU","sector_code":null,"is_leaf":false,"children_count":0},{"code":"LU.06","title":"Trade Union Federation","level":2,"parent_code":"LU","sector_code":null,"is_leaf":false,"children_count":0},{"code":"LU.07","title":"Enterprise Union","level":2,"parent_code":"LU","sector_code":null,"is_leaf":false,"children_count":0},{"code":"LU.08","title":"Works Council","level":2,"parent_code":"LU","sector_code":null,"is_leaf":false,"children_count":0},{"code":"LU.09","title":"Professional Association (Union)","level":2,"parent_code":"LU","sector_code":null,"is_leaf":false,"children_count":0},{"code":"LU.10","title":"Union Density Rate","level":2,"parent_code":"LU","sector_code":null,"is_leaf":false,"children_count":0},{"code":"LU.11","title":"Right-to-Work State","level":2,"parent_code":"LU","sector_code":null,"is_leaf":false,"children_count":0},{"code":"LU.12","title":"Union Certification Process","level":2,"parent_code":"LU","sector_code":null,"is_leaf":false,"children_count":0}]