[{"code":"dcss_carbon","title":"Embodied Carbon and Material Health","level":1,"parent_code":null,"sector_code":"carbon","is_leaf":false,"children_count":4},{"code":"dcss_energy","title":"Energy Performance Certification","level":1,"parent_code":null,"sector_code":"energy","is_leaf":false,"children_count":4},{"code":"dcss_finance","title":"Green Financing and Incentive Programs","level":1,"parent_code":null,"sector_code":"finance","is_leaf":false,"children_count":3},{"code":"dcss_leed","title":"LEED and Green Building Rating Systems","level":1,"parent_code":null,"sector_code":"leed","is_leaf":false,"children_count":5},{"code":"dcss_resilience","title":"Resilience and Climate Adaptation Standards","level":1,"parent_code":null,"sector_code":"resilience","is_leaf":false,"children_count":3},{"code":"dcss_carbon_declare","title":"Declare and Chemicals of Concern Disclosure","level":2,"parent_code":"dcss_carbon","sector_code":"carbon","is_leaf":true,"children_count":0},{"code":"dcss_carbon_epd","title":"Environmental Product Declaration (EPD - PCR)","level":2,"parent_code":"dcss_carbon","sector_code":"carbon","is_leaf":true,"children_count":0},{"code":"dcss_carbon_lca","title":"Life Cycle Assessment (LCA - ISO 14040/44)","level":2,"parent_code":"dcss_carbon","sector_code":"carbon","is_leaf":true,"children_count":0},{"code":"dcss_carbon_living","title":"Living Building Challenge (LBC - regenerative)","level":2,"parent_code":"dcss_carbon","sector_code":"carbon","is_leaf":true,"children_count":0},{"code":"dcss_energy_ashrae","title":"ASHRAE 90.1 Advanced Energy Design Guide","level":2,"parent_code":"dcss_energy","sector_code":"energy","is_leaf":true,"children_count":0},{"code":"dcss_energy_energy_star","title":"ENERGY STAR Certification (EPA, commercial bldg)","level":2,"parent_code":"dcss_energy","sector_code":"energy","is_leaf":true,"children_count":0},{"code":"dcss_energy_passive","title":"Passive House (PHI Certified, PHIUS+)","level":2,"parent_code":"dcss_energy","sector_code":"energy","is_leaf":true,"children_count":0},{"code":"dcss_energy_zne","title":"Zero Net Energy (ZNE) and Net Zero Carbon","level":2,"parent_code":"dcss_energy","sector_code":"energy","is_leaf":true,"children_count":0},{"code":"dcss_finance_bond","title":"Green Bond and Sustainability-Linked Loan","level":2,"parent_code":"dcss_finance","sector_code":"finance","is_leaf":true,"children_count":0},{"code":"dcss_finance_ira","title":"IRA Clean Energy Tax Credit (179D, 45L, 48C)","level":2,"parent_code":"dcss_finance","sector_code":"finance","is_leaf":true,"children_count":0},{"code":"dcss_finance_rebate","title":"Utility Rebate and Incentive Program","level":2,"parent_code":"dcss_finance","sector_code":"finance","is_leaf":true,"children_count":0},{"code":"dcss_leed_bdnc","title":"LEED BD+C (Building Design and Construction)","level":2,"parent_code":"dcss_leed","sector_code":"leed","is_leaf":true,"children_count":0},{"code":"dcss_leed_breeam","title":"BREEAM (Building Research Establishment, UK/intl)","level":2,"parent_code":"dcss_leed","sector_code":"leed","is_leaf":true,"children_count":0},{"code":"dcss_leed_green_globes","title":"Green Globes (North American rating system)","level":2,"parent_code":"dcss_leed","sector_code":"leed","is_leaf":true,"children_count":0},{"code":"dcss_leed_id","title":"LEED ID+C (Interior Design and Construction)","level":2,"parent_code":"dcss_leed","sector_code":"leed","is_leaf":true,"children_count":0},{"code":"dcss_leed_om","title":"LEED O+M (Operations and Maintenance)","level":2,"parent_code":"dcss_leed","sector_code":"leed","is_leaf":true,"children_count":0},{"code":"dcss_resilience_fortified","title":"IBHS FORTIFIED Construction Standard","level":2,"parent_code":"dcss_resilience","sector_code":"resilience","is_leaf":true,"children_count":0},{"code":"dcss_resilience_reset","title":"RESET Building Performance Standard","level":2,"parent_code":"dcss_resilience","sector_code":"resilience","is_leaf":true,"children_count":0},{"code":"dcss_resilience_well","title":"WELL Building Standard (health and wellness)","level":2,"parent_code":"dcss_resilience","sector_code":"resilience","is_leaf":true,"children_count":0}]