[{"code":"ddfacq_acat","title":"US DoD ACAT Programme Categories","level":1,"parent_code":null,"sector_code":"acat","is_leaf":false,"children_count":4},{"code":"ddfacq_contract","title":"Contract Instrument Types","level":1,"parent_code":null,"sector_code":"contract","is_leaf":false,"children_count":5},{"code":"ddfacq_intl","title":"International and Non-US Acquisition Frameworks","level":1,"parent_code":null,"sector_code":"intl","is_leaf":false,"children_count":3},{"code":"ddfacq_phase","title":"Acquisition Lifecycle Phases","level":1,"parent_code":null,"sector_code":"phase","is_leaf":false,"children_count":5},{"code":"ddfacq_acat_i","title":"ACAT I - Major Defence Acquisition Programs (MDAP)","level":2,"parent_code":"ddfacq_acat","sector_code":"acat","is_leaf":true,"children_count":0},{"code":"ddfacq_acat_ii","title":"ACAT II - Major Automated Information Systems (MAIS)","level":2,"parent_code":"ddfacq_acat","sector_code":"acat","is_leaf":true,"children_count":0},{"code":"ddfacq_acat_iii","title":"ACAT III - Less than ACAT II or MDAP thresholds","level":2,"parent_code":"ddfacq_acat","sector_code":"acat","is_leaf":true,"children_count":0},{"code":"ddfacq_acat_iv","title":"ACAT IV - Component or lower command acquisitions","level":2,"parent_code":"ddfacq_acat","sector_code":"acat","is_leaf":true,"children_count":0},{"code":"ddfacq_contract_cpaf","title":"Cost-Plus-Award-Fee (CPAF) contracts","level":2,"parent_code":"ddfacq_contract","sector_code":"contract","is_leaf":true,"children_count":0},{"code":"ddfacq_contract_cpff","title":"Cost-Plus-Fixed-Fee (CPFF) contracts","level":2,"parent_code":"ddfacq_contract","sector_code":"contract","is_leaf":true,"children_count":0},{"code":"ddfacq_contract_ffp","title":"Firm-Fixed-Price (FFP) contracts","level":2,"parent_code":"ddfacq_contract","sector_code":"contract","is_leaf":true,"children_count":0},{"code":"ddfacq_contract_fpif","title":"Fixed-Price Incentive Firm (FPIF) contracts","level":2,"parent_code":"ddfacq_contract","sector_code":"contract","is_leaf":true,"children_count":0},{"code":"ddfacq_contract_idiq","title":"Indefinite Delivery / Indefinite Quantity (IDIQ)","level":2,"parent_code":"ddfacq_contract","sector_code":"contract","is_leaf":true,"children_count":0},{"code":"ddfacq_intl_dcs","title":"Direct Commercial Sales (DCS) and export licensing","level":2,"parent_code":"ddfacq_intl","sector_code":"intl","is_leaf":true,"children_count":0},{"code":"ddfacq_intl_fms","title":"US Foreign Military Sales (FMS) programme","level":2,"parent_code":"ddfacq_intl","sector_code":"intl","is_leaf":true,"children_count":0},{"code":"ddfacq_intl_nato","title":"NATO Capability Development (NDPP, NCI Agency)","level":2,"parent_code":"ddfacq_intl","sector_code":"intl","is_leaf":true,"children_count":0},{"code":"ddfacq_phase_frr","title":"Full-Rate Production Decision Review","level":2,"parent_code":"ddfacq_phase","sector_code":"phase","is_leaf":true,"children_count":0},{"code":"ddfacq_phase_matdev","title":"Material Development Decision (MDD) / Concept","level":2,"parent_code":"ddfacq_phase","sector_code":"phase","is_leaf":true,"children_count":0},{"code":"ddfacq_phase_msb","title":"Milestone B - Engineering and Manufacturing Development","level":2,"parent_code":"ddfacq_phase","sector_code":"phase","is_leaf":true,"children_count":0},{"code":"ddfacq_phase_msc","title":"Milestone C - Production and Deployment","level":2,"parent_code":"ddfacq_phase","sector_code":"phase","is_leaf":true,"children_count":0},{"code":"ddfacq_phase_ops","title":"Operations and Support (sustainment phase)","level":2,"parent_code":"ddfacq_phase","sector_code":"phase","is_leaf":true,"children_count":0}]