[{"code":"ICD10CA","title":"ICD-10-CA Chapters","level":1,"parent_code":null,"sector_code":null,"is_leaf":false,"children_count":22},{"code":"I","title":"Certain infectious and parasitic diseases","level":2,"parent_code":"ICD10CA","sector_code":null,"is_leaf":false,"children_count":0},{"code":"II","title":"Neoplasms","level":2,"parent_code":"ICD10CA","sector_code":null,"is_leaf":false,"children_count":0},{"code":"III","title":"Blood diseases and immune disorders","level":2,"parent_code":"ICD10CA","sector_code":null,"is_leaf":false,"children_count":0},{"code":"IV","title":"Endocrine, nutritional and metabolic","level":2,"parent_code":"ICD10CA","sector_code":null,"is_leaf":false,"children_count":0},{"code":"IX","title":"Circulatory system diseases","level":2,"parent_code":"ICD10CA","sector_code":null,"is_leaf":false,"children_count":0},{"code":"V","title":"Mental and behavioural disorders","level":2,"parent_code":"ICD10CA","sector_code":null,"is_leaf":false,"children_count":0},{"code":"VI","title":"Nervous system diseases","level":2,"parent_code":"ICD10CA","sector_code":null,"is_leaf":false,"children_count":0},{"code":"VII","title":"Eye and adnexa diseases","level":2,"parent_code":"ICD10CA","sector_code":null,"is_leaf":false,"children_count":0},{"code":"VIII","title":"Ear and mastoid diseases","level":2,"parent_code":"ICD10CA","sector_code":null,"is_leaf":false,"children_count":0},{"code":"X","title":"Respiratory system diseases","level":2,"parent_code":"ICD10CA","sector_code":null,"is_leaf":false,"children_count":0},{"code":"XI","title":"Digestive system diseases","level":2,"parent_code":"ICD10CA","sector_code":null,"is_leaf":false,"children_count":0},{"code":"XII","title":"Skin and subcutaneous tissue","level":2,"parent_code":"ICD10CA","sector_code":null,"is_leaf":false,"children_count":0},{"code":"XIII","title":"Musculoskeletal and connective tissue","level":2,"parent_code":"ICD10CA","sector_code":null,"is_leaf":false,"children_count":0},{"code":"XIV","title":"Genitourinary system","level":2,"parent_code":"ICD10CA","sector_code":null,"is_leaf":false,"children_count":0},{"code":"XIX","title":"Injury, poisoning and external causes","level":2,"parent_code":"ICD10CA","sector_code":null,"is_leaf":false,"children_count":0},{"code":"XV","title":"Pregnancy, childbirth and puerperium","level":2,"parent_code":"ICD10CA","sector_code":null,"is_leaf":false,"children_count":0},{"code":"XVI","title":"Perinatal conditions","level":2,"parent_code":"ICD10CA","sector_code":null,"is_leaf":false,"children_count":0},{"code":"XVII","title":"Congenital malformations","level":2,"parent_code":"ICD10CA","sector_code":null,"is_leaf":false,"children_count":0},{"code":"XVIII","title":"Symptoms and abnormal findings","level":2,"parent_code":"ICD10CA","sector_code":null,"is_leaf":false,"children_count":0},{"code":"XX","title":"External causes of morbidity","level":2,"parent_code":"ICD10CA","sector_code":null,"is_leaf":false,"children_count":0},{"code":"XXI","title":"Health status and health services","level":2,"parent_code":"ICD10CA","sector_code":null,"is_leaf":false,"children_count":0},{"code":"XXII","title":"Special purpose codes","level":2,"parent_code":"ICD10CA","sector_code":null,"is_leaf":false,"children_count":0}]