[{"code":"LT","title":"Lean Tools","level":1,"parent_code":null,"sector_code":null,"is_leaf":false,"children_count":14},{"code":"LT.01","title":"5S (Sort, Set, Shine, Standardize, Sustain)","level":2,"parent_code":"LT","sector_code":null,"is_leaf":false,"children_count":0},{"code":"LT.02","title":"Value Stream Mapping (VSM)","level":2,"parent_code":"LT","sector_code":null,"is_leaf":false,"children_count":0},{"code":"LT.03","title":"Kanban","level":2,"parent_code":"LT","sector_code":null,"is_leaf":false,"children_count":0},{"code":"LT.04","title":"Kaizen (Continuous Improvement)","level":2,"parent_code":"LT","sector_code":null,"is_leaf":false,"children_count":0},{"code":"LT.05","title":"Poka-Yoke (Error Proofing)","level":2,"parent_code":"LT","sector_code":null,"is_leaf":false,"children_count":0},{"code":"LT.06","title":"Just-in-Time (JIT)","level":2,"parent_code":"LT","sector_code":null,"is_leaf":false,"children_count":0},{"code":"LT.07","title":"Andon (Visual Signal)","level":2,"parent_code":"LT","sector_code":null,"is_leaf":false,"children_count":0},{"code":"LT.08","title":"Gemba Walk","level":2,"parent_code":"LT","sector_code":null,"is_leaf":false,"children_count":0},{"code":"LT.09","title":"Heijunka (Level Loading)","level":2,"parent_code":"LT","sector_code":null,"is_leaf":false,"children_count":0},{"code":"LT.10","title":"SMED (Quick Changeover)","level":2,"parent_code":"LT","sector_code":null,"is_leaf":false,"children_count":0},{"code":"LT.11","title":"Total Productive Maintenance (TPM)","level":2,"parent_code":"LT","sector_code":null,"is_leaf":false,"children_count":0},{"code":"LT.12","title":"A3 Problem Solving","level":2,"parent_code":"LT","sector_code":null,"is_leaf":false,"children_count":0},{"code":"LT.13","title":"Hoshin Kanri (Policy Deployment)","level":2,"parent_code":"LT","sector_code":null,"is_leaf":false,"children_count":0},{"code":"LT.14","title":"Takt Time","level":2,"parent_code":"LT","sector_code":null,"is_leaf":false,"children_count":0}]