[{"code":"N12","title":"NAICS 2012 Sectors","level":1,"parent_code":null,"sector_code":null,"is_leaf":false,"children_count":20},{"code":"N12.11","title":"Agriculture, Forestry, Fishing","level":2,"parent_code":"N12","sector_code":null,"is_leaf":false,"children_count":0},{"code":"N12.21","title":"Mining, Quarrying, Oil/Gas","level":2,"parent_code":"N12","sector_code":null,"is_leaf":false,"children_count":0},{"code":"N12.22","title":"Utilities","level":2,"parent_code":"N12","sector_code":null,"is_leaf":false,"children_count":0},{"code":"N12.23","title":"Construction","level":2,"parent_code":"N12","sector_code":null,"is_leaf":false,"children_count":0},{"code":"N12.31","title":"Manufacturing (31-33)","level":2,"parent_code":"N12","sector_code":null,"is_leaf":false,"children_count":0},{"code":"N12.42","title":"Wholesale Trade","level":2,"parent_code":"N12","sector_code":null,"is_leaf":false,"children_count":0},{"code":"N12.44","title":"Retail Trade (44-45)","level":2,"parent_code":"N12","sector_code":null,"is_leaf":false,"children_count":0},{"code":"N12.48","title":"Transportation and Warehousing (48-49)","level":2,"parent_code":"N12","sector_code":null,"is_leaf":false,"children_count":0},{"code":"N12.51","title":"Information","level":2,"parent_code":"N12","sector_code":null,"is_leaf":false,"children_count":0},{"code":"N12.52","title":"Finance and Insurance","level":2,"parent_code":"N12","sector_code":null,"is_leaf":false,"children_count":0},{"code":"N12.53","title":"Real Estate","level":2,"parent_code":"N12","sector_code":null,"is_leaf":false,"children_count":0},{"code":"N12.54","title":"Professional Services","level":2,"parent_code":"N12","sector_code":null,"is_leaf":false,"children_count":0},{"code":"N12.55","title":"Management of Companies","level":2,"parent_code":"N12","sector_code":null,"is_leaf":false,"children_count":0},{"code":"N12.56","title":"Admin and Support","level":2,"parent_code":"N12","sector_code":null,"is_leaf":false,"children_count":0},{"code":"N12.61","title":"Educational Services","level":2,"parent_code":"N12","sector_code":null,"is_leaf":false,"children_count":0},{"code":"N12.62","title":"Health Care","level":2,"parent_code":"N12","sector_code":null,"is_leaf":false,"children_count":0},{"code":"N12.71","title":"Arts and Recreation","level":2,"parent_code":"N12","sector_code":null,"is_leaf":false,"children_count":0},{"code":"N12.72","title":"Accommodation and Food","level":2,"parent_code":"N12","sector_code":null,"is_leaf":false,"children_count":0},{"code":"N12.81","title":"Other Services","level":2,"parent_code":"N12","sector_code":null,"is_leaf":false,"children_count":0},{"code":"N12.92","title":"Public Administration","level":2,"parent_code":"N12","sector_code":null,"is_leaf":false,"children_count":0}]