[{"code":"WA","title":"Work Activities","level":1,"parent_code":null,"sector_code":null,"is_leaf":false,"children_count":15},{"code":"WA.01","title":"Information Input","level":2,"parent_code":"WA","sector_code":null,"is_leaf":false,"children_count":0},{"code":"WA.02","title":"Mental Processes","level":2,"parent_code":"WA","sector_code":null,"is_leaf":false,"children_count":0},{"code":"WA.03","title":"Work Output","level":2,"parent_code":"WA","sector_code":null,"is_leaf":false,"children_count":0},{"code":"WA.04","title":"Interacting With Others","level":2,"parent_code":"WA","sector_code":null,"is_leaf":false,"children_count":0},{"code":"WA.05","title":"Looking at Data","level":2,"parent_code":"WA","sector_code":null,"is_leaf":false,"children_count":0},{"code":"WA.06","title":"Identifying Objects/Actions","level":2,"parent_code":"WA","sector_code":null,"is_leaf":false,"children_count":0},{"code":"WA.07","title":"Estimating Characteristics","level":2,"parent_code":"WA","sector_code":null,"is_leaf":false,"children_count":0},{"code":"WA.08","title":"Judging Quality","level":2,"parent_code":"WA","sector_code":null,"is_leaf":false,"children_count":0},{"code":"WA.09","title":"Processing Information","level":2,"parent_code":"WA","sector_code":null,"is_leaf":false,"children_count":0},{"code":"WA.10","title":"Evaluating Information","level":2,"parent_code":"WA","sector_code":null,"is_leaf":false,"children_count":0},{"code":"WA.11","title":"Making Decisions","level":2,"parent_code":"WA","sector_code":null,"is_leaf":false,"children_count":0},{"code":"WA.12","title":"Creative Thinking","level":2,"parent_code":"WA","sector_code":null,"is_leaf":false,"children_count":0},{"code":"WA.13","title":"Updating Knowledge","level":2,"parent_code":"WA","sector_code":null,"is_leaf":false,"children_count":0},{"code":"WA.14","title":"Scheduling Work","level":2,"parent_code":"WA","sector_code":null,"is_leaf":false,"children_count":0},{"code":"WA.15","title":"Organizing and Planning","level":2,"parent_code":"WA","sector_code":null,"is_leaf":false,"children_count":0}]