[{"code":"arch","title":"Architecture, Infrastructure, and Operations Booklet","level":1,"parent_code":null,"sector_code":"arch","is_leaf":true,"children_count":0},{"code":"audit","title":"Audit Booklet","level":1,"parent_code":null,"sector_code":"audit","is_leaf":true,"children_count":0},{"code":"bcp","title":"Business Continuity Management Booklet","level":1,"parent_code":null,"sector_code":"bcp","is_leaf":false,"children_count":4},{"code":"cat_tool","title":"Cybersecurity Assessment Tool (CAT)","level":1,"parent_code":null,"sector_code":"cat","is_leaf":false,"children_count":2},{"code":"dev_acq","title":"Development, Acquisition, and Maintenance Booklet","level":1,"parent_code":null,"sector_code":"dev","is_leaf":true,"children_count":0},{"code":"ebanking","title":"E-Banking Booklet","level":1,"parent_code":null,"sector_code":"ebanking","is_leaf":true,"children_count":0},{"code":"info_sec","title":"Information Security Booklet","level":1,"parent_code":null,"sector_code":"info","is_leaf":false,"children_count":6},{"code":"mgmt","title":"Management Booklet","level":1,"parent_code":null,"sector_code":"mgmt","is_leaf":true,"children_count":0},{"code":"ops","title":"Operations Booklet","level":1,"parent_code":null,"sector_code":"ops","is_leaf":true,"children_count":0},{"code":"outsource","title":"Outsourcing Technology Services Booklet","level":1,"parent_code":null,"sector_code":"outsource","is_leaf":true,"children_count":0},{"code":"payments","title":"Retail Payment Systems Booklet","level":1,"parent_code":null,"sector_code":"payments","is_leaf":true,"children_count":0},{"code":"supervision","title":"Supervision of Technology Service Providers Booklet","level":1,"parent_code":null,"sector_code":"supervision","is_leaf":true,"children_count":0},{"code":"wholesale","title":"Wholesale Payment Systems Booklet","level":1,"parent_code":null,"sector_code":"wholesale","is_leaf":true,"children_count":0},{"code":"bcp_bia","title":"Business Impact Analysis","level":2,"parent_code":"bcp","sector_code":"bcp","is_leaf":true,"children_count":0},{"code":"bcp_risk","title":"Risk Assessment","level":2,"parent_code":"bcp","sector_code":"bcp","is_leaf":true,"children_count":0},{"code":"bcp_strategy","title":"Recovery Strategy","level":2,"parent_code":"bcp","sector_code":"bcp","is_leaf":true,"children_count":0},{"code":"bcp_testing","title":"Testing and Exercises","level":2,"parent_code":"bcp","sector_code":"bcp","is_leaf":true,"children_count":0},{"code":"cat_inherent","title":"Inherent Risk Profile (CAT)","level":2,"parent_code":"cat_tool","sector_code":"cat","is_leaf":true,"children_count":0},{"code":"cat_maturity","title":"Cybersecurity Maturity (CAT)","level":2,"parent_code":"cat_tool","sector_code":"cat","is_leaf":true,"children_count":0},{"code":"is_controls","title":"Security Controls","level":2,"parent_code":"info_sec","sector_code":"is","is_leaf":true,"children_count":0},{"code":"is_governance","title":"Information Security Governance","level":2,"parent_code":"info_sec","sector_code":"is","is_leaf":true,"children_count":0},{"code":"is_incident","title":"Incident Response","level":2,"parent_code":"info_sec","sector_code":"is","is_leaf":true,"children_count":0},{"code":"is_monitoring","title":"Security Monitoring","level":2,"parent_code":"info_sec","sector_code":"is","is_leaf":true,"children_count":0},{"code":"is_risk","title":"Risk Assessment","level":2,"parent_code":"info_sec","sector_code":"is","is_leaf":true,"children_count":0},{"code":"is_testing","title":"Security Testing","level":2,"parent_code":"info_sec","sector_code":"is","is_leaf":true,"children_count":0}]