[{"code":"disclosure","title":"Disclosure Regulations","level":1,"parent_code":null,"sector_code":"disclosure","is_leaf":false,"children_count":8},{"code":"enforcement_sec","title":"Enforcement Framework","level":1,"parent_code":null,"sector_code":"enforcement","is_leaf":false,"children_count":3},{"code":"governance","title":"Corporate Governance Regulations","level":1,"parent_code":null,"sector_code":"governance","is_leaf":false,"children_count":4},{"code":"registration","title":"Registration and Offering Regulations","level":1,"parent_code":null,"sector_code":"registration","is_leaf":false,"children_count":4},{"code":"trading","title":"Trading and Market Regulations","level":1,"parent_code":null,"sector_code":"trading","is_leaf":false,"children_count":5},{"code":"admin_proceedings","title":"Administrative Proceedings","level":2,"parent_code":"enforcement_sec","sector_code":"admin","is_leaf":true,"children_count":0},{"code":"beneficial_own","title":"Beneficial Ownership Reporting (13d, 13f, 13g)","level":2,"parent_code":"governance","sector_code":"beneficial","is_leaf":true,"children_count":0},{"code":"civil_actions","title":"Civil Actions in Federal Court","level":2,"parent_code":"enforcement_sec","sector_code":"civil","is_leaf":true,"children_count":0},{"code":"form_10k","title":"Form 10-K Annual Report Requirements","level":2,"parent_code":"disclosure","sector_code":"form","is_leaf":true,"children_count":0},{"code":"form_10q","title":"Form 10-Q Quarterly Report Requirements","level":2,"parent_code":"disclosure","sector_code":"form","is_leaf":true,"children_count":0},{"code":"form_8k","title":"Form 8-K Current Report Requirements","level":2,"parent_code":"disclosure","sector_code":"form","is_leaf":true,"children_count":0},{"code":"insider_trading","title":"Insider Trading Rules (Section 16, Rule 10b5-1)","level":2,"parent_code":"governance","sector_code":"insider","is_leaf":true,"children_count":0},{"code":"penalties","title":"Disgorgement and Civil Monetary Penalties","level":2,"parent_code":"enforcement_sec","sector_code":"penalties","is_leaf":true,"children_count":0},{"code":"proxy_rules","title":"Proxy Rules (14a Series)","level":2,"parent_code":"governance","sector_code":"proxy","is_leaf":true,"children_count":0},{"code":"reg_a","title":"Regulation A - Small Offerings (17 CFR 230.251-263)","level":2,"parent_code":"registration","sector_code":"reg","is_leaf":true,"children_count":0},{"code":"reg_ats","title":"Regulation ATS - Alternative Trading Systems (17 CFR 242.300-303)","level":2,"parent_code":"trading","sector_code":"reg","is_leaf":true,"children_count":0},{"code":"reg_cf","title":"Regulation Crowdfunding (17 CFR 227)","level":2,"parent_code":"registration","sector_code":"reg","is_leaf":true,"children_count":0},{"code":"reg_d","title":"Regulation D - Private Placements (17 CFR 230.500-508)","level":2,"parent_code":"registration","sector_code":"reg","is_leaf":true,"children_count":0},{"code":"reg_fd","title":"Regulation FD - Fair Disclosure (17 CFR 243)","level":2,"parent_code":"disclosure","sector_code":"reg","is_leaf":true,"children_count":0},{"code":"reg_g","title":"Regulation G - Non-GAAP Financial Measures (17 CFR 244)","level":2,"parent_code":"disclosure","sector_code":"reg","is_leaf":true,"children_count":0},{"code":"reg_nms","title":"Regulation NMS - National Market System (17 CFR 242)","level":2,"parent_code":"trading","sector_code":"reg","is_leaf":true,"children_count":0},{"code":"reg_s","title":"Regulation S - Offshore Offerings (17 CFR 230.901-905)","level":2,"parent_code":"registration","sector_code":"reg","is_leaf":true,"children_count":0},{"code":"reg_sci","title":"Regulation SCI - Systems Compliance and Integrity","level":2,"parent_code":"trading","sector_code":"reg","is_leaf":true,"children_count":0},{"code":"reg_sho","title":"Regulation SHO - Short Sales (17 CFR 242.200-204)","level":2,"parent_code":"trading","sector_code":"reg","is_leaf":true,"children_count":0},{"code":"reg_sk","title":"Regulation S-K - Non-Financial Statement Disclosures (17 CFR 229)","level":2,"parent_code":"disclosure","sector_code":"reg","is_leaf":true,"children_count":0},{"code":"reg_sx","title":"Regulation S-X - Financial Statement Requirements (17 CFR 210)","level":2,"parent_code":"disclosure","sector_code":"reg","is_leaf":true,"children_count":0},{"code":"rule_10b5","title":"Rule 10b-5 - Employment of Manipulative and Deceptive Devices","level":2,"parent_code":"trading","sector_code":"rule","is_leaf":true,"children_count":0},{"code":"whistleblower","title":"SEC Whistleblower Program (Rule 21F)","level":2,"parent_code":"governance","sector_code":"whistleblower","is_leaf":true,"children_count":0},{"code":"xbrl","title":"Inline XBRL Requirements","level":2,"parent_code":"disclosure","sector_code":"xbrl","is_leaf":true,"children_count":0}]