[{"code":"SK","title":"SKOS Concepts","level":1,"parent_code":null,"sector_code":null,"is_leaf":false,"children_count":16},{"code":"SK.01","title":"Concept (skos:Concept)","level":2,"parent_code":"SK","sector_code":null,"is_leaf":false,"children_count":0},{"code":"SK.02","title":"ConceptScheme","level":2,"parent_code":"SK","sector_code":null,"is_leaf":false,"children_count":0},{"code":"SK.03","title":"Collection","level":2,"parent_code":"SK","sector_code":null,"is_leaf":false,"children_count":0},{"code":"SK.04","title":"OrderedCollection","level":2,"parent_code":"SK","sector_code":null,"is_leaf":false,"children_count":0},{"code":"SK.05","title":"prefLabel","level":2,"parent_code":"SK","sector_code":null,"is_leaf":false,"children_count":0},{"code":"SK.06","title":"altLabel","level":2,"parent_code":"SK","sector_code":null,"is_leaf":false,"children_count":0},{"code":"SK.07","title":"hiddenLabel","level":2,"parent_code":"SK","sector_code":null,"is_leaf":false,"children_count":0},{"code":"SK.08","title":"broader","level":2,"parent_code":"SK","sector_code":null,"is_leaf":false,"children_count":0},{"code":"SK.09","title":"narrower","level":2,"parent_code":"SK","sector_code":null,"is_leaf":false,"children_count":0},{"code":"SK.10","title":"related","level":2,"parent_code":"SK","sector_code":null,"is_leaf":false,"children_count":0},{"code":"SK.11","title":"broadMatch","level":2,"parent_code":"SK","sector_code":null,"is_leaf":false,"children_count":0},{"code":"SK.12","title":"narrowMatch","level":2,"parent_code":"SK","sector_code":null,"is_leaf":false,"children_count":0},{"code":"SK.13","title":"closeMatch","level":2,"parent_code":"SK","sector_code":null,"is_leaf":false,"children_count":0},{"code":"SK.14","title":"exactMatch","level":2,"parent_code":"SK","sector_code":null,"is_leaf":false,"children_count":0},{"code":"SK.15","title":"notation","level":2,"parent_code":"SK","sector_code":null,"is_leaf":false,"children_count":0},{"code":"SK.16","title":"definition/note/scopeNote","level":2,"parent_code":"SK","sector_code":null,"is_leaf":false,"children_count":0}]